README.md
setup.py
tmsc/__init__.py
tmsc/__main__.py
tmsc/environment.py
tmsc/topic_detector.py
tmsc.egg-info/PKG-INFO
tmsc.egg-info/SOURCES.txt
tmsc.egg-info/dependency_links.txt
tmsc.egg-info/entry_points.txt
tmsc.egg-info/requires.txt
tmsc.egg-info/top_level.txt