Metadata-Version: 1.1
Name: tmsc
Version: 0.1.4a0
Summary: Part of source{d}'s stack for machine learning on source code. Provides API and tools to detect topics in Git repositories.
Home-page: https://github.com/src-d/tmsc
Author: source{d}
Author-email: machine-learning@sourced.tech
License: Apache Software License
Download-URL: https://github.com/src-d/tmsc
Keywords: machine learning on source code,topic modeling,github,bblfsh,babelfish,ast2vec
Platform: UNKNOWN
Classifier: Development Status :: 3 - Alpha
Classifier: Environment :: Console
Classifier: Intended Audience :: Developers
Classifier: License :: OSI Approved :: Apache Software License
Classifier: Operating System :: POSIX
Classifier: Programming Language :: Python :: 3.4
Classifier: Programming Language :: Python :: 3.5
Classifier: Programming Language :: Python :: 3.6
Classifier: Topic :: Software Development :: Libraries
